README.md
setup.py
pulumiverse_purrl/__init__.py
pulumiverse_purrl/_utilities.py
pulumiverse_purrl/provider.py
pulumiverse_purrl/pulumi-plugin.json
pulumiverse_purrl/purrl.py
pulumiverse_purrl/py.typed
pulumiverse_purrl.egg-info/PKG-INFO
pulumiverse_purrl.egg-info/SOURCES.txt
pulumiverse_purrl.egg-info/dependency_links.txt
pulumiverse_purrl.egg-info/not-zip-safe
pulumiverse_purrl.egg-info/requires.txt
pulumiverse_purrl.egg-info/top_level.txt